assetra/__init__.py
assetra/contribution.py
assetra/metrics.py
assetra/simulation.py
assetra/system.py
assetra/units.py
assetra-2025.8.20.dist-info/LICENSE
assetra-2025.8.20.dist-info/METADATA
assetra-2025.8.20.dist-info/WHEEL
assetra-2025.8.20.dist-info/RECORD
