Metadata-Version: 2.1
Name: assetra
Version: 2025.8.20
Summary: ASSET Lab Resource Adequacy Package
License: MIT
Author: Isaac Bromley-Dulfano
Author-email: ijbd@umich.edu
Requires-Python: >=3.10,<4.0
Classifier: License :: OSI Approved :: MIT License
Classifier: Programming Language :: Python :: 3
Classifier: Programming Language :: Python :: 3.10
Classifier: Programming Language :: Python :: 3.11
Classifier: Programming Language :: Python :: 3.12
Classifier: Programming Language :: Python :: 3.13
Requires-Dist: netCDF4 (>=1.7.2,<2.0.0)
Requires-Dist: xarray (>=2024.10.0,<2025.0.0)
